nonebot_plugin_auto_bot_selector-0.2.1.dist-info/METADATA
nonebot_plugin_auto_bot_selector-0.2.1.dist-info/WHEEL
nonebot_plugin_auto_bot_selector-0.2.1.dist-info/licenses/LICENSE
nonebot_plugin_auto_bot_selector/__init__.py
nonebot_plugin_auto_bot_selector/adapters/__init__.py
nonebot_plugin_auto_bot_selector/adapters/dodo.py
nonebot_plugin_auto_bot_selector/adapters/kaiheila.py
nonebot_plugin_auto_bot_selector/adapters/onebot_v11.py
nonebot_plugin_auto_bot_selector/adapters/onebot_v12.py
nonebot_plugin_auto_bot_selector/adapters/qq.py
nonebot_plugin_auto_bot_selector/adapters/red.py
nonebot_plugin_auto_bot_selector/adapters/satori.py
nonebot_plugin_auto_bot_selector/expection.py
nonebot_plugin_auto_bot_selector/registries.py
nonebot_plugin_auto_bot_selector/target.py
nonebot_plugin_auto_bot_selector/utils/alconna.py
nonebot_plugin_auto_bot_selector-0.2.1.dist-info/RECORD
