Metadata-Version: 2.1
Name: nonebot-plugin-auto-bot-selector
Version: 0.2.1
Summary: 自动Bot选择器，消息推送好帮手
Author-Email: Well404 <well_404@outlook.com>
License: MIT
Requires-Python: >=3.8
Requires-Dist: nonebot2>=2.2.1
Requires-Dist: typing-extensions>=4.11.0
Requires-Dist: nonebot-adapter-onebot>=2.4.3; extra == "dev"
Requires-Dist: nonebot-adapter-qq>=1.4.3; extra == "dev"
Requires-Dist: nonebot-adapter-red>=0.9.0; extra == "dev"
Requires-Dist: nonebot-adapter-satori>=0.10.4; extra == "dev"
Requires-Dist: nonebot-adapter-dodo>=0.2.1; extra == "dev"
Requires-Dist: nonebot-adapter-kaiheila>=0.3.3; extra == "dev"
Requires-Dist: nonebot-plugin-alconna>=0.42.3; extra == "dev"
Provides-Extra: dev
